json_verifier/__init__.py
json_verifier/json_verifier.py
json_verifier-0.6.1.dist-info/METADATA
json_verifier-0.6.1.dist-info/WHEEL
json_verifier-0.6.1.dist-info/licenses/LICENSE
json_verifier-0.6.1.dist-info/RECORD
