Metadata-Version: 2.4
Name: json-verifier
Version: 0.6.1
Summary: Allows a test to spot-check various values of a JSON object
Author-email: Hai Vu <haivu2004@gmail.com>
License-Expression: MIT
License-File: LICENSE
Keywords: json,pytest
Classifier: Development Status :: 4 - Beta
Classifier: Programming Language :: Python
Classifier: Programming Language :: Python :: 3.9
Classifier: Programming Language :: Python :: 3.10
Classifier: Programming Language :: Python :: 3.11
Classifier: Programming Language :: Python :: 3.12
Classifier: Programming Language :: Python :: 3.13
Classifier: Programming Language :: Python :: 3.14
Classifier: Programming Language :: Python :: Implementation :: CPython
Classifier: Programming Language :: Python :: Implementation :: PyPy
Requires-Python: >=3.9
